fO2calculate/__init__.py
fO2calculate/activitycoefficients.py
fO2calculate/batch_calculate.py
fO2calculate/batchfile.py
fO2calculate/calculate.py
fO2calculate/core.py
fO2calculate/interactionparameters.py
fO2calculate/sample_class.py
tests/__init__.py
tests/test_activities.py
tests/test_sample.py
fO2calculate-0.1.0.dist-info/LICENSE
fO2calculate-0.1.0.dist-info/METADATA
fO2calculate-0.1.0.dist-info/WHEEL
fO2calculate-0.1.0.dist-info/top_level.txt
fO2calculate-0.1.0.dist-info/RECORD
